multi_db_query_builder/__init__.py
multi_db_query_builder/bigquery_query_builder.py
multi_db_query_builder/constants.py
multi_db_query_builder/database_object_handler.py
multi_db_query_builder/multi_database_query_builder.py
multi_db_query_builder/postgresql_query_builder.py
multi_db_query_builder/protocol_class.py
multi_db_query_builder/snowflake_query_builder.py
multi_db_query_builder-1.1.dist-info/METADATA
multi_db_query_builder-1.1.dist-info/WHEEL
multi_db_query_builder-1.1.dist-info/top_level.txt
multi_db_query_builder-1.1.dist-info/RECORD
