Metadata-Version: 2.1
Name: multi_db_query_builder
Version: 1.1
Summary: Simplify SQL queries across databases
Home-page: https://bitbucket.org/ChandaniStepFunction/db_query_builder
Author: Mukesh Prasad
Author-email: mukesh@stepfunction.ai
Classifier: Programming Language :: Python :: 3
Classifier: License :: OSI Approved :: MIT License
Classifier: Operating System :: OS Independent
Requires-Python: >=3.8
Requires-Dist: SQLAlchemy
Requires-Dist: snowflake-connector-python
Requires-Dist: snowflake-snowpark-python
Requires-Dist: snowflake-sqlalchemy
Requires-Dist: sqlalchemy-bigquery
Requires-Dist: sqlalchemy-redshift
Requires-Dist: redshift-connector
Requires-Dist: psycopg2-binary
